aliyunsdkdataworks_public/__init__.py
aliyunsdkdataworks_public/endpoint.py
aliyunsdkdataworks_public/request/__init__.py
aliyunsdkdataworks_public/request/v20200518/AbolishDataServiceApiRequest.py
aliyunsdkdataworks_public/request/v20200518/AddMetaCollectionEntityRequest.py
aliyunsdkdataworks_public/request/v20200518/AddProjectMemberToRoleRequest.py
aliyunsdkdataworks_public/request/v20200518/AddRecognizeRuleRequest.py
aliyunsdkdataworks_public/request/v20200518/AddToMetaCategoryRequest.py
aliyunsdkdataworks_public/request/v20200518/ApprovePermissionApplyOrderRequest.py
aliyunsdkdataworks_public/request/v20200518/CallbackExtensionRequest.py
aliyunsdkdataworks_public/request/v20200518/ChangeResourceManagerResourceGroupRequest.py
aliyunsdkdataworks_public/request/v20200518/CheckFileDeploymentRequest.py
aliyunsdkdataworks_public/request/v20200518/CheckMetaPartitionRequest.py
aliyunsdkdataworks_public/request/v20200518/CheckMetaTableRequest.py
aliyunsdkdataworks_public/request/v20200518/CreateBaselineRequest.py
aliyunsdkdataworks_public/request/v20200518/CreateBusinessRequest.py
aliyunsdkdataworks_public/request/v20200518/CreateConnectionRequest.py
aliyunsdkdataworks_public/request/v20200518/CreateDIAlarmRuleRequest.py
aliyunsdkdataworks_public/request/v20200518/CreateDIJobRequest.py
aliyunsdkdataworks_public/request/v20200518/CreateDISyncTaskRequest.py
aliyunsdkdataworks_public/request/v20200518/CreateDagComplementRequest.py
aliyunsdkdataworks_public/request/v20200518/CreateDagTestRequest.py
aliyunsdkdataworks_public/request/v20200518/CreateDataServiceApiAuthorityRequest.py
aliyunsdkdataworks_public/request/v20200518/CreateDataServiceApiRequest.py
aliyunsdkdataworks_public/request/v20200518/CreateDataServiceFolderRequest.py
aliyunsdkdataworks_public/request/v20200518/CreateDataServiceGroupRequest.py
aliyunsdkdataworks_public/request/v20200518/CreateDataSourceRequest.py
aliyunsdkdataworks_public/request/v20200518/CreateExportMigrationRequest.py
aliyun_python_sdk_dataworks_public-6.1.12.dist-info/LICENSE
aliyun_python_sdk_dataworks_public-6.1.12.dist-info/METADATA
aliyun_python_sdk_dataworks_public-6.1.12.dist-info/WHEEL
aliyun_python_sdk_dataworks_public-6.1.12.dist-info/top_level.txt
aliyun_python_sdk_dataworks_public-6.1.12.dist-info/RECORD
